takiyasha/__init__.py
takiyasha/__main__.py
takiyasha/argdefs.py
takiyasha/constants.py
takiyasha/core.py
takiyasha/entry.py
takiyasha/utils.py
takiyasha/tag/__init__.py
takiyasha/tag/complete.py
takiyasha/tag/read.py
takiyasha/tag/retrieve_convert.py
takiyasha/tag/utils.py
takiyasha/tag/write.py
takiyasha-0.7.0.dist-info/LICENSE
takiyasha-0.7.0.dist-info/METADATA
takiyasha-0.7.0.dist-info/WHEEL
takiyasha-0.7.0.dist-info/entry_points.txt
takiyasha-0.7.0.dist-info/top_level.txt
takiyasha-0.7.0.dist-info/RECORD
