Metadata-Version: 2.1
Name: takiyasha
Version: 0.7.0
Summary: Python 音乐解密工具
Author: nukemiko
License: MIT License        
Project-URL: Homepage, https://github.com/nukemiko/takiyasha
Project-URL: Documentation, https://github.com/nukemiko/takiyasha/wiki
Project-URL: Bug Tracker, https://github.com/nukemiko/takiyasha/issues
Project-URL: Releases, https://github.com/nukemiko/takiyasha/releases
Keywords: unlock,music,audio,qmc,ncm,mflac,mgg,netease,163,qqmusic
Classifier: License :: OSI Approved :: MIT License
Classifier: Operating System :: OS Independent
Classifier: Topic :: Multimedia :: Sound/Audio
Classifier: Programming Language :: Python :: 3.8
Classifier: Programming Language :: Python :: 3.9
Classifier: Programming Language :: Python :: 3.10
Requires-Python: >=3.8
License-File: LICENSE
Requires-Dist: mutagen
Requires-Dist: MusicTagFindUtils (>=0.1.2)
Requires-Dist: colorama
Requires-Dist: requests
Requires-Dist: libtakiyasha (==1.1.0)
